{"stats":{"minecraft:used":{"minecraft:stone_axe":10,"minecraft:acacia_boat":3,"minecraft:nether_bricks":18,"minecraft:white_terracotta":1,"minecraft:acacia_planks":3,"minecraft:netherrack":40,"minecraft:iron_sword":137,"minecraft:water_bucket":3,"minecraft:wooden_axe":32,"minecraft:jungle_planks":11,"minecraft:cooked_porkchop":5,"minecraft:bread":26,"minecraft:dirt":14,"minecraft:cut_sandstone":4,"minecraft:lava_bucket":10,"minecraft:wooden_hoe":30,"minecraft:orange_bed":2,"minecraft:wooden_pickaxe":79,"minecraft:brown_mushroom":1,"minecraft:crimson_fungus":1,"minecraft:basalt":12,"minecraft:cobblestone":27,"minecraft:jungle_pressure_plate":1,"minecraft:bucket":13,"minecraft:crafting_table":6,"minecraft:chest":1,"minecraft:blackstone":27,"minecraft:nether_brick_slab":6,"minecraft:jungle_slab":1,"minecraft:brown_wool":3,"minecraft:stone_pickaxe":97},"minecraft:mined":{"minecraft:vine":6,"minecraft:chest":1,"minecraft:netherrack":36,"minecraft:wheat":3,"minecraft:white_terracotta":1,"minecraft:hay_block":27,"minecraft:cobblestone":3,"minecraft:gravel":9,"minecraft:short_grass":115,"minecraft:acacia_leaves":1,"minecraft:furnace":1,"minecraft:crafting_table":3,"minecraft:jungle_log":13,"minecraft:tall_grass":21,"minecraft:jungle_slab":1,"minecraft:blackstone":21,"minecraft:dirt":11,"minecraft:jungle_planks":2,"minecraft:grass_block":6,"minecraft:nether_bricks":32,"minecraft:cut_sandstone":3,"minecraft:nether_brick_fence":2,"minecraft:basalt":22,"minecraft:fern":8,"minecraft:fire":11,"minecraft:orange_bed":5,"minecraft:acacia_wood":3,"minecraft:dead_bush":4,"minecraft:jungle_leaves":2,"minecraft:acacia_log":3,"minecraft:stone":42},"minecraft:crafted":{"minecraft:flint_and_steel":1,"minecraft:bucket":2,"minecraft:wooden_axe":1,"minecraft:jungle_planks":52,"minecraft:nether_brick_slab":6,"minecraft:golden_boots":1,"minecraft:gold_ingot":3,"minecraft:stone_pickaxe":1,"minecraft:bread":64,"minecraft:crafting_table":3,"minecraft:stick":8,"minecraft:wooden_hoe":1,"minecraft:jungle_pressure_plate":1,"minecraft:wooden_pickaxe":2,"minecraft:shield":1,"minecraft:iron_sword":1,"minecraft:acacia_planks":24,"minecraft:wheat":252},"minecraft:custom":{"minecraft:time_since_rest":23848,"minecraft:leave_game":4,"minecraft:damage_taken":1837,"minecraft:mob_kills":39,"minecraft:boat_one_cm":177026,"minecraft:time_since_death":23742,"minecraft:sleep_in_bed":1,"minecraft:total_world_time":96827,"minecraft:swim_one_cm":18583,"minecraft:crouch_one_cm":70743,"minecraft:deaths":3,"minecraft:climb_one_cm":1133,"minecraft:damage_blocked_by_shield":40,"minecraft:interact_with_crafting_table":15,"minecraft:walk_one_cm":81379,"minecraft:horse_one_cm":348551,"minecraft:walk_under_water_one_cm":1063,"minecraft:play_time":96827,"minecraft:damage_dealt":8597,"minecraft:jump":2000,"minecraft:drop":18,"minecraft:sprint_one_cm":225087,"minecraft:open_chest":15,"minecraft:fall_one_cm":41431,"minecraft:fly_one_cm":415530,"minecraft:walk_on_water_one_cm":3342,"minecraft:sneak_time":22328},"minecraft:killed":{"minecraft:zombie":2,"minecraft:husk":2,"minecraft:sheep":17,"minecraft:iron_golem":1,"minecraft:pig":6,"minecraft:cow":3,"minecraft:villager":1,"minecraft:camel":1,"minecraft:blaze":5,"minecraft:spider":1},"minecraft:picked_up":{"minecraft:cobblestone":39,"minecraft:saddle":1,"minecraft:camel_spawn_egg":1,"minecraft:flint":2,"minecraft:leather":2,"minecraft:gold_nugget":33,"minecraft:lead":1,"minecraft:brown_mushroom":1,"minecraft:stone_pickaxe":1,"minecraft:gold_ingot":3,"minecraft:white_terracotta":1,"minecraft:blaze_rod":9,"minecraft:emerald":3,"minecraft:crimson_roots":2,"minecraft:porkchop":12,"minecraft:stick":11,"minecraft:crimson_fungus":1,"minecraft:acacia_slab":5,"minecraft:black_wool":1,"minecraft:cooked_porkchop":47,"minecraft:iron_ingot":11,"minecraft:jungle_slab":2,"minecraft:acacia_wood":3,"minecraft:hay_block":28,"minecraft:cow_spawn_egg":1,"minecraft:stone_axe":1,"minecraft:acacia_log":3,"minecraft:wheat":1,"minecraft:leather_helmet":1,"minecraft:mutton":24,"minecraft:chest":1,"minecraft:cut_sandstone":4,"minecraft:blackstone":27,"minecraft:netherrack":47,"minecraft:dirt":14,"minecraft:husk_spawn_egg":1,"minecraft:basalt":22,"minecraft:brown_wool":10,"minecraft:blaze_spawn_egg":1,"minecraft:gravel":8,"minecraft:jungle_planks":2,"minecraft:light_gray_wool":4,"minecraft:acacia_boat":4,"minecraft:nether_brick_fence":2,"minecraft:furnace":1,"minecraft:wheat_seeds":17,"minecraft:jungle_log":13,"minecraft:nether_bricks":30,"minecraft:birch_sapling":4,"minecraft:poppy":9,"minecraft:white_wool":2,"minecraft:sheep_spawn_egg":2,"minecraft:crafting_table":3,"minecraft:rotten_flesh":1,"minecraft:written_book":2,"minecraft:beef":4,"minecraft:apple":38,"minecraft:orange_bed":5},"minecraft:broken":{"minecraft:wooden_pickaxe":1},"minecraft:dropped":{"minecraft:jungle_slab":1,"minecraft:rotten_flesh":1,"minecraft:filled_map":1,"minecraft:gravel":8,"minecraft:written_book":2,"minecraft:stick":1,"minecraft:poppy":9,"minecraft:gold_nugget":4,"minecraft:wheat_seeds":7,"minecraft:iron_ingot":5,"minecraft:gold_ingot":2,"minecraft:recovery_compass":1,"minecraft:cooked_porkchop":38}},"DataVersion":4438}